CHANGES.rst
MANIFEST.in
README.rst
setup.py
pathspec/__init__.py
pathspec/compat.py
pathspec/gitignore.py
pathspec/pathspec.py
pathspec/pattern.py
pathspec/util.py
pathspec.egg-info/PKG-INFO
pathspec.egg-info/SOURCES.txt
pathspec.egg-info/dependency_links.txt
pathspec.egg-info/top_level.txt
pathspec/tests/__init__.py
pathspec/tests/test_gitignore.py