Metadata-Version: 1.1
Name: pathspec
Version: 0.2.2
Summary: Utility library for gitignore style pattern matching of file paths.
Home-page: https://github.com/cpburnz/python-path-specification
Author: Caleb P. Burns
Author-email: cpburnz@gmail.com
License: MPL 2.0
Platform: UNKNOWN
Classifier: Development Status :: 4 - Beta
Classifier: Intended Audience :: Developers
Classifier: License :: OSI Approved :: Mozilla Public License 2.0 (MPL 2.0)
Classifier: Operating System :: OS Independent
Classifier: Programming Language :: Python
Classifier: Programming Language :: Python :: 2
Classifier: Programming Language :: Python :: 2.7
Classifier: Programming Language :: Python :: 3
Classifier: Topic :: Software Development :: Libraries :: Python Modules
Classifier: Topic :: Utilities
